pymelhorenvio/__init__.py
pymelhorenvio/account.py
pymelhorenvio/address.py
pymelhorenvio/cart.py
pymelhorenvio/config.py
pymelhorenvio/freight_item.py
pymelhorenvio/freight_service.py
pymelhorenvio/infra/__init__.py
pymelhorenvio/infra/http_client/__init__.py
pymelhorenvio/infra/http_client/fake_http_client.py
pymelhorenvio/melhor_envio.py
pymelhorenvio/order.py
pymelhorenvio/package.py
pymelhorenvio/receiver.py
pymelhorenvio/sender.py
pymelhorenvio/shipment.py
pymelhorenvio-0.0.6.dist-info/METADATA
pymelhorenvio-0.0.6.dist-info/WHEEL
pymelhorenvio-0.0.6.dist-info/RECORD
