Metadata-Version: 2.1
Name: pymelhorenvio
Version: 0.0.6
Summary: 
Author: Erick Duarte
Author-email: erickod@gmail.com
Requires-Python: >=3.7,<4.0
Classifier: Programming Language :: Python :: 3
Classifier: Programming Language :: Python :: 3.7
Classifier: Programming Language :: Python :: 3.8
Classifier: Programming Language :: Python :: 3.9
Classifier: Programming Language :: Python :: 3.10
Classifier: Programming Language :: Python :: 3.11
Requires-Dist: httpx (>=0.21.3,<0.22.0)
